[
  {
    "full_name": "Peter Parker",
    "phone_number": "321654879",
    "email": "pp@yahoo.com",
    "tags": "friend",
    "id": 4
  },
  {
    "full_name": "Albert Einstein",
    "phone_number": "2145876125",
    "email": "einstein@science.com",
    "tags": "work,friend",
    "id": 6
  },
  {
    "full_name": "Nick Fury",
    "phone_number": "1232435345456",
    "email": "nf@yahoo.com",
    "tags": "friend",
    "id": 7
  },
  {
    "full_name": "Thor Odinson",
    "phone_number": "3",
    "email": "thor@asgard.com",
    "tags": "",
    "id": 8
  },
  {
    "full_name": "Hulk",
    "phone_number": "515988973",
    "email": "hulk@live.com",
    "tags": "work,family",
    "id": 9
  }
]